{
    "AX": {
        "error": 0.003903760309814889,
        "error_type": "SEM",
        "filter_outliers_dict": {
            "filter_outliers": false,
            "iterations": 1,
            "std_devs": 2
        },
        "fit": "average",
        "value": -0.025848608971952788
    },
    "CDD": {
        "error": 4.867193892601504e-06,
        "error_type": "SEM",
        "filter_outliers_dict": {
            "filter_outliers": false,
            "iterations": 1,
            "std_devs": 2
        },
        "fit": "average",
        "value": -1.3046255774472786e-05
    },
    "H1": {
        "error": 0.009588040498647537,
        "error_type": "SEM",
        "filter_outliers_dict": {
            "filter_outliers": false,
            "iterations": 1,
            "std_devs": 2
        },
        "fit": "average",
        "value": -0.15525622606150208
    },
    "H2": {
        "error": 0.009340928588636659,
        "error_type": "SEM",
        "filter_outliers_dict": {
            "filter_outliers": false,
            "iterations": 1,
            "std_devs": 2
        },
        "fit": "average",
        "value": -0.0903558294263111
    },
    "L1": {
        "error": 0.009974459397860708,
        "error_type": "SEM",
        "filter_outliers_dict": {
            "filter_outliers": false,
            "iterations": 1,
            "std_devs": 2
        },
        "fit": "average",
        "value": -0.034890354003129155
    },
    "L2": {
        "error": 0.004691726103771838,
        "error_type": "SEM",
        "filter_outliers_dict": {
            "filter_outliers": false,
            "iterations": 1,
            "std_devs": 2
        },
        "fit": "average",
        "value": 0.001337282455874554
    }
}